expd/__init__.py
expd/_cli.py
expd/dependencies.py
expd/artifacts/artifacts.py
expd/artifacts/protocols.py
expd/dtypes/__init__.py
expd/dtypes/dtypes.py
expd/dtypes/dtyping.py
expd/dtypes/elements.py
expd/dtypes/models.py
expd/notebooks/explorer.py
expd/notebooks/runner.py
expd/notebooks/trial.py
expd/notebooks/viewer.py
expd/results/__init__.py
expd/results/env.py
expd/results/load_trial.py
expd/results/results.py
expd/results/schemas.py
expd/strategies/__init__.py
expd/strategies/base.py
expd/strategies/container.py
expd/strategies/gaussian.py
expd/strategies/grid.py
expd/strategies/uniform.py
expd/strategies/utils.py
expd/utils/parse_dataclass.py
expd-0.1.1.dist-info/METADATA
expd-0.1.1.dist-info/WHEEL
expd-0.1.1.dist-info/entry_points.txt
expd-0.1.1.dist-info/licenses/LICENSE
expd-0.1.1.dist-info/RECORD
