Metadata-Version: 2.3
Name: expd
Version: 0.1.1
Summary: A framework for running computational experiments, powered by marimo notebooks
Project-URL: homepage, https://github.com/marimo-team/expd
License-File: LICENSE
Requires-Python: >=3.9
Requires-Dist: annotated-types>=0.7.0
Requires-Dist: click>=8.0
Requires-Dist: marimo>=0.9.10
Requires-Dist: psutil>=6.0.0
Requires-Dist: pynvml>=11.5.3
Provides-Extra: artifacts
Requires-Dist: numpy>=2.0.0; extra == 'artifacts'
Requires-Dist: pillow>=10.4.0; extra == 'artifacts'
Requires-Dist: scipy>=1.13.0; extra == 'artifacts'
Requires-Dist: torch>=2.0.0; extra == 'artifacts'
Provides-Extra: dev
Requires-Dist: mypy~=1.12.0; extra == 'dev'
Requires-Dist: pytest~=8.3.3; extra == 'dev'
Requires-Dist: ruff~=0.6.3; extra == 'dev'
Requires-Dist: types-psutil>=6.0.0.20241011; extra == 'dev'
Requires-Dist: typos~=1.23.6; extra == 'dev'
